autosecretkey/__init__.py
django_autosecretkey-0.9.2.dist-info/LICENSE
django_autosecretkey-0.9.2.dist-info/METADATA
django_autosecretkey-0.9.2.dist-info/WHEEL
django_autosecretkey-0.9.2.dist-info/top_level.txt
django_autosecretkey-0.9.2.dist-info/RECORD
